veris_ai/README.md
veris_ai/__init__.py
veris_ai/agents_wrapper.py
veris_ai/api_client.py
veris_ai/context_vars.py
veris_ai/jwt_utils.py
veris_ai/logfire_config.py
veris_ai/logger.py
veris_ai/models.py
veris_ai/observability.py
veris_ai/tool_mock.py
veris_ai/utils.py
veris_ai/jaeger_interface/README.md
veris_ai/jaeger_interface/__init__.py
veris_ai/jaeger_interface/client.py
veris_ai/jaeger_interface/models.py
veris_ai-1.26.0.dist-info/METADATA
veris_ai-1.26.0.dist-info/WHEEL
veris_ai-1.26.0.dist-info/licenses/LICENSE
veris_ai-1.26.0.dist-info/RECORD
