Metadata-Version: 2.4
Name: veris-ai
Version: 1.26.0
Summary: A Python package for Veris AI tools
Project-URL: Homepage, https://github.com/veris-ai/veris-python-sdk
Project-URL: Bug Tracker, https://github.com/veris-ai/veris-python-sdk/issues
Author-email: Mehdi Jamei <mehdi@veris.ai>
License-Expression: MIT
License-File: LICENSE
Requires-Python: >=3.11
Requires-Dist: httpx>=0.24.0
Requires-Dist: logfire>=4.3.3
Requires-Dist: opentelemetry-api>=1.34.1
Requires-Dist: opentelemetry-exporter-otlp>=1.34.1
Requires-Dist: opentelemetry-instrumentation-fastapi>=0.55b1
Requires-Dist: opentelemetry-instrumentation-httpx>=0.55b1
Requires-Dist: opentelemetry-instrumentation-mcp>=0.44.1
Requires-Dist: opentelemetry-instrumentation-requests>=0.55b1
Requires-Dist: opentelemetry-instrumentation>=0.55b1
Requires-Dist: opentelemetry-sdk>=1.34.1
Requires-Dist: pydantic>=2.0.0
Requires-Dist: pyjwt[crypto]>=2.8.0
Requires-Dist: requests>=2.31.0
Requires-Dist: tenacity>=9.1.2
Provides-Extra: agents
Requires-Dist: openai-agents>=0.2.5; extra == 'agents'
Provides-Extra: dev
Requires-Dist: mypy>=1.17.0; extra == 'dev'
Requires-Dist: pre-commit>=3.3.3; extra == 'dev'
Requires-Dist: pytest-asyncio>=1.1.0; extra == 'dev'
Requires-Dist: pytest-cov>=6.2.1; extra == 'dev'
Requires-Dist: pytest>=8.4.1; extra == 'dev'
Requires-Dist: ruff>=0.12.4; extra == 'dev'
Requires-Dist: types-requests>=2.32.4.20250611; extra == 'dev'
Requires-Dist: uvicorn>=0.30.0; extra == 'dev'
Provides-Extra: fastapi
Requires-Dist: fastapi-mcp>=0.4.0; extra == 'fastapi'
Requires-Dist: fastapi>=0.116.1; extra == 'fastapi'
Provides-Extra: instrument
Requires-Dist: wrapt>=1.14.0; extra == 'instrument'
